tes33423312/__init__.py
tes33423312/circle_calculator.py
tes33423312-0.0.1.dist-info/METADATA
tes33423312-0.0.1.dist-info/WHEEL
tes33423312-0.0.1.dist-info/top_level.txt
tes33423312-0.0.1.dist-info/RECORD
