Metadata-Version: 2.1
Name: tes33423312
Version: 0.0.1
Summary: tes33423312
Home-page: 
Author: 
Author-email: 
License: MIT
Keywords: luas,lingkaran
Classifier: Development Status :: 1 - Planning
